RA3BattleNetData/BattleNetData.py
RA3BattleNetData/__init__.py
ra3battlenetdata-0.0.1.dist-info/licenses/LICENSE
ra3battlenetdata-0.0.1.dist-info/METADATA
ra3battlenetdata-0.0.1.dist-info/WHEEL
ra3battlenetdata-0.0.1.dist-info/top_level.txt
ra3battlenetdata-0.0.1.dist-info/RECORD
