Metadata-Version: 2.4
Name: RA3BattleNetData
Version: 0.0.1
Summary: 获取红警三战网房间json数据
Author: Kunagisa
Author-email: 1549184870@qq.com
License: Apache-2.0
Keywords: RA3BattleNet
License-File: LICENSE
Requires-Dist: requests>=2.14.0
Requires-Dist: requests-toolbelt>=1.0.0
Dynamic: author
Dynamic: author-email
Dynamic: description-content-type
Dynamic: keywords
Dynamic: license
Dynamic: license-file
Dynamic: requires-dist
Dynamic: summary
